ChangeLog
LICENSE
MANIFEST.in
README
setup.py
bin/tftpy_client.py
bin/tftpy_server.py
tftpy/TftpClient.py
tftpy/TftpContexts.py
tftpy/TftpPacketFactory.py
tftpy/TftpPacketTypes.py
tftpy/TftpServer.py
tftpy/TftpShared.py
tftpy/TftpStates.py
tftpy/__init__.py
tftpy/compat.py
tftpy.egg-info/PKG-INFO
tftpy.egg-info/SOURCES.txt
tftpy.egg-info/dependency_links.txt
tftpy.egg-info/top_level.txt